<place name="Place_T1_DepartureSecurity"><value item="Queue" itemname="PAX Queue" name="QueueId" value="1"/><value item="Queue" itemname="PAX Queue" name="QueueLength" value="9"/><value item="Queue" itemname="PAX Queue" name="WaitB" value="47"/><value item="Queue" itemname="PAX Queue" name="WaitDisplay" value="60"/><value item="Desk" itemname="INTDSEC 01" name="ProcessTime" value="100"/><value item="Desk" itemname="INTDSEC 02" name="ProcessTime" value="0"/><value item="Desk" itemname="INTDSEC 03" name="ProcessTime" value="56"/><value item="Desk" itemname="INTDSEC 04" name="ProcessTime" value="0"/><value item="Desk" itemname="INTDSEC 05" name="ProcessTime" value="0"/><value item="Desk" itemname="INTDSEC 06" name="ProcessTime" value="111"/><value item="Desk" itemname="INTDSEC 07" name="ProcessTime" value="0"/><value item="Desk" itemname="INTDSEC 08" name="ProcessTime" value="75"/><value item="Desk" itemname="INTDSEC 09" name="ProcessTime" value="25"/><value item="Error" itemname="" name="" value="0"/></place>